brational/__init__.py
brational/brat.py
brational/util.py
brational-2.0.1.dist-info/licenses/LICENSE
brational-2.0.1.dist-info/METADATA
brational-2.0.1.dist-info/WHEEL
brational-2.0.1.dist-info/top_level.txt
brational-2.0.1.dist-info/RECORD
