Metadata-Version: 2.4
Name: brational
Version: 2.0.1
Summary: A SageMath package to beautifully format rational functions arising from enumerative algebra into plaintext and latex.
Home-page: https://joshmaglione.com/BRational/
Author: Joshua Maglione
Author-email: joshmaglione@gmail.com
Project-URL: Bug Tracker, https://github.com/joshmaglione/brational/issues
Keywords: SageMath,rational functions,generating series,formatting
Classifier: Programming Language :: Python :: 3
Classifier: License :: OSI Approved :: MIT License
Classifier: Operating System :: OS Independent
License-File: LICENSE
Dynamic: license-file
